homeassistantdesktop/__init__.py
homeassistantdesktop/__main__.py
homeassistantdesktop/_version.py
homeassistantdesktop-1.0.0.dev1.dist-info/METADATA
homeassistantdesktop-1.0.0.dev1.dist-info/WHEEL
homeassistantdesktop-1.0.0.dev1.dist-info/top_level.txt
homeassistantdesktop-1.0.0.dev1.dist-info/RECORD
